modelhub/__init__.py
modelhub/aggregate.py
modelhub/decorators.py
modelhub/map.py
modelhub/metrics.py
modelhub/modelhub.py
modelhub/py.typed
modelhub/util.py
modelhub/models/__init__.py
modelhub/models/funnel_discovery.py
modelhub/models/logistic_regression.py
modelhub/pipelines/__init__.py
modelhub/pipelines/base_pipeline.py
modelhub/pipelines/extracted_contexts.py
modelhub/pipelines/identity_resolution.py
modelhub/pipelines/sessionized_data.py
modelhub/pipelines/util.py
modelhub/series/__init__.py
modelhub/series/series_objectiv.py
objectiv_modelhub-0.0.28.dist-info/METADATA
objectiv_modelhub-0.0.28.dist-info/WHEEL
objectiv_modelhub-0.0.28.dist-info/top_level.txt
objectiv_modelhub-0.0.28.dist-info/RECORD
