Metadata-Version: 2.1
Name: objectiv-modelhub
Version: 0.0.28
Summary: The open model hub is a growing collection of data models that you can take, combine and run for product analysis and exploration.
Home-page: https://github.com/objectiv/objectiv-analytics/
Author: Objectiv B.V.
Author-email: hi@objectiv.io
License: Apache License 2.0
Project-URL: Documentation, https://objectiv.io/docs
Project-URL: Bug Tracker, https://github.com/objectiv/objectiv-analytics/issues
Classifier: Programming Language :: Python :: 3
Classifier: License :: OSI Approved :: Apache Software License
Classifier: Operating System :: OS Independent
Classifier: Development Status :: 4 - Beta
Requires-Python: >=3.7
Requires-Dist: sqlalchemy (<=1.4.27)
Requires-Dist: pyarrow (<7.0dev)
Requires-Dist: objectiv-bach[bigquery] (==0.0.28)
Requires-Dist: requests
Requires-Dist: matplotlib
Requires-Dist: seaborn
Requires-Dist: plotly
Requires-Dist: scikit-learn
Requires-Dist: typing-extensions
Provides-Extra: dev
Requires-Dist: mypy (==0.910) ; extra == 'dev'
Requires-Dist: pycodestyle (==2.7.0) ; extra == 'dev'
Requires-Dist: pytest (==6.2.5) ; extra == 'dev'
Requires-Dist: pytest-env ; extra == 'dev'
Requires-Dist: pytest-xdist (==2.5.0) ; extra == 'dev'
Requires-Dist: filelock (==3.7.1) ; extra == 'dev'
Requires-Dist: types-requests ; extra == 'dev'
Requires-Dist: python-dotenv (==0.20.0) ; extra == 'dev'
Requires-Dist: pyathena (>=2.10.0) ; extra == 'dev'
